aranea/__init__.py
aranea/apg/__init__.py
aranea/apg/compose_attack_path_graph.py
aranea/apg/get_component_node_feasibility_rating.py
aranea/apg/get_networkx_graph.py
aranea/apg/get_reduced_graph.py
aranea/apg/get_shortest_path.py
aranea/apg/utils/attack_path_node_positioner.py
aranea/apg/utils/get_positioned_component_nodes.py
aranea/dff/__init__.py
aranea/dff/build_diff_graph.py
aranea/dff/build_tabular_diff_representation.py
aranea/dff/export_dff_excel.py
aranea/dff/get_graph_diff.py
aranea/dff/node_placer.py
aranea/dff/utils.py
aranea/g2d/__init__.py
aranea/g2d/style_configs/get_default_style_config.py
aranea/g2d/text_node_constants.py
aranea/g2d/transform_component_node_to_mx_cell.py
aranea/g2d/transform_edge_to_mx_cell.py
aranea/g2d/transform_graph_collection_to_mx_file.py
aranea/g2d/transform_graph_to_diagram.py
aranea/g2d/transform_network_to_mx_cells.py
aranea/g2d/transform_networks_to_mx_cells.py
aranea/g2d/transform_nodes_to_mx_cells.py
aranea/g2d/transform_technical_capabilities_to_mx_cells.py
aranea/g2d/transform_text_node_to_mx_cell.py
aranea/g2d/transform_waypoint_node_to_mx_cell.py
aranea/g2d/transform_xor_node_to_mx_cell.py
aranea/g2d/utils/get_graph_boundaries.py
aranea/g2d/utils/get_graph_key.py
aranea/g2d/utils/get_graph_label.py
aranea/g2d/utils/get_graph_model_page_size.py
aranea/ge/__init__.py
aranea/ge/excel_names.py
aranea/ge/graph_collection_enricher.py
aranea/models/__init__.py
aranea/models/config_model.py
aranea/models/custom_xml_shapes/__init__.py
aranea/models/custom_xml_shapes/custom_xml_shapes_utils.py
aranea/models/custom_xml_shapes/icons/amg_icon.svg.jinja
aranea/models/custom_xml_shapes/icons/analog_broadcast_icon.svg.jinja
aranea/models/custom_xml_shapes/icons/backend_icon.svg.jinja
aranea/models/custom_xml_shapes/icons/bluetooth_icon.svg.jinja
aranea/models/custom_xml_shapes/icons/car_charger_icon.svg.jinja
aranea/models/custom_xml_shapes/icons/cellular_icon.svg.jinja
aranea-1.0.3.dist-info/LICENSE
aranea-1.0.3.dist-info/METADATA
aranea-1.0.3.dist-info/WHEEL
aranea-1.0.3.dist-info/entry_points.txt
aranea-1.0.3.dist-info/RECORD
